tomas/__init__.py
tomas/auxi.py
tomas/fit.py
tomas/infer.py
tomas/lrt.py
tomas/vis.py
tomas-0.1.1.dist-info/LICENSE
tomas-0.1.1.dist-info/METADATA
tomas-0.1.1.dist-info/WHEEL
tomas-0.1.1.dist-info/top_level.txt
tomas-0.1.1.dist-info/RECORD
