Metadata-Version: 2.1
Name: tomas
Version: 0.1.1
Summary: A tool for TOtal-MRNA-Aware Single-cell RNA-seq data analysis
Home-page: https://tomas.readthedocs.io/en/latest/
Author: Qiuyu Lian
Author-email: qiuyu.lian@sjtu.edu.cn
License: BSD-3
License-File: LICENSE
Requires-Dist: pyDIMM (==0.1.0)
Requires-Dist: scanpy (>=1.7.1)
